README.rst
setup.py
scalerunner/__init__.py
scalerunner/driver.py
scalerunner.egg-info/PKG-INFO
scalerunner.egg-info/SOURCES.txt
scalerunner.egg-info/dependency_links.txt
scalerunner.egg-info/requires.txt
scalerunner.egg-info/top_level.txt